sciform/__init__.py
sciform/api/__init__.py
sciform/api/formatted_number.py
sciform/api/formatter.py
sciform/api/global_configuration.py
sciform/api/scinum.py
sciform/format_utils/__init__.py
sciform/format_utils/exp_translations.py
sciform/format_utils/exponents.py
sciform/format_utils/grouping.py
sciform/format_utils/make_strings.py
sciform/format_utils/numbers.py
sciform/format_utils/rounding.py
sciform/formatting/__init__.py
sciform/formatting/fsml.py
sciform/formatting/number_formatting.py
sciform/formatting/output_conversion.py
sciform/formatting/parser.py
sciform/options/__init__.py
sciform/options/conversion.py
sciform/options/finalized_options.py
sciform/options/global_options.py
sciform/options/input_options.py
sciform/options/option_types.py
sciform/options/populated_options.py
sciform/options/validation.py
sciform-0.39.1.dist-info/licenses/LICENSE
sciform-0.39.1.dist-info/METADATA
sciform-0.39.1.dist-info/WHEEL
sciform-0.39.1.dist-info/top_level.txt
sciform-0.39.1.dist-info/RECORD
