Metadata-Version: 2.4
Name: sciform
Version: 0.39.1
Summary: A package for formatting numbers into scientific formatted strings.
Author-email: Justin Gerber <justin.gerber48@gmail.com>
Project-URL: homepage, https://github.com/jagerber48/sciform
Project-URL: documentation, https://sciform.readthedocs.io
Classifier: License :: OSI Approved :: MIT License
Classifier: Development Status :: 4 - Beta
Classifier: Programming Language :: Python
Classifier: Programming Language :: Python :: 3
Classifier: Programming Language :: Python :: 3.8
Classifier: Programming Language :: Python :: 3.9
Classifier: Programming Language :: Python :: 3.10
Classifier: Programming Language :: Python :: 3.11
Classifier: Programming Language :: Python :: 3.12
Classifier: Topic :: Education
Classifier: Topic :: Scientific/Engineering
Classifier: Topic :: Text Processing
Classifier: Topic :: Utilities
Requires-Python: >=3.8
License-File: LICENSE
Provides-Extra: docs
Requires-Dist: sphinx; extra == "docs"
Requires-Dist: sphinx-rtd-dark-mode; extra == "docs"
Requires-Dist: sphinx-rtd-theme; extra == "docs"
Requires-Dist: sphinx-toolbox; extra == "docs"
Provides-Extra: test
Requires-Dist: coverage[toml]; extra == "test"
Requires-Dist: numpy; extra == "test"
Requires-Dist: ruff==0.5.5; extra == "test"
Requires-Dist: sciform[docs]; extra == "test"
Provides-Extra: examples
Requires-Dist: numpy; extra == "examples"
Requires-Dist: scipy; extra == "examples"
Requires-Dist: matplotlib; extra == "examples"
Requires-Dist: tabulate; extra == "examples"
Requires-Dist: jupyter; extra == "examples"
Provides-Extra: all
Requires-Dist: sciform[docs]; extra == "all"
Requires-Dist: sciform[test]; extra == "all"
Requires-Dist: sciform[examples]; extra == "all"
Dynamic: license-file
